pyhamcrest_toolbox/__init__.py
pyhamcrest_toolbox/multicomponent.py
pyhamcrest_toolbox/util.py
pyhamcrest_toolbox/wrapper_base.py
pyhamcrest_toolbox/wrappers.py
pyhamcrest_toolbox-0.3.0.dist-info/LICENSE
pyhamcrest_toolbox-0.3.0.dist-info/METADATA
pyhamcrest_toolbox-0.3.0.dist-info/WHEEL
pyhamcrest_toolbox-0.3.0.dist-info/top_level.txt
pyhamcrest_toolbox-0.3.0.dist-info/RECORD
